notepaper/__init__.py
notepaper/paper.py
notepaper-0.0.2.dist-info/METADATA
notepaper-0.0.2.dist-info/WHEEL
notepaper-0.0.2.dist-info/top_level.txt
notepaper-0.0.2.dist-info/RECORD
