Metadata-Version: 2.1
Name: notepaper
Version: 0.0.2
Summary: notepaper
Home-page: https://github.com/1007530194
Author: niuliangtao
Author-email: 1007530194@qq.com
License: UNKNOWN
Platform: UNKNOWN
